aibs_informatics_aws_utils/__init__.py
aibs_informatics_aws_utils/_version.py
aibs_informatics_aws_utils/apigateway.py
aibs_informatics_aws_utils/athena.py
aibs_informatics_aws_utils/auth.py
aibs_informatics_aws_utils/batch.py
aibs_informatics_aws_utils/core.py
aibs_informatics_aws_utils/ec2.py
aibs_informatics_aws_utils/ecs.py
aibs_informatics_aws_utils/exceptions.py
aibs_informatics_aws_utils/fsx.py
aibs_informatics_aws_utils/lambda_.py
aibs_informatics_aws_utils/logs.py
aibs_informatics_aws_utils/py.typed
aibs_informatics_aws_utils/s3.py
aibs_informatics_aws_utils/secretsmanager.py
aibs_informatics_aws_utils/ses.py
aibs_informatics_aws_utils/sns.py
aibs_informatics_aws_utils/sqs.py
aibs_informatics_aws_utils/ssm.py
aibs_informatics_aws_utils/stepfn.py
aibs_informatics_aws_utils/constants/__init__.py
aibs_informatics_aws_utils/constants/efs.py
aibs_informatics_aws_utils/constants/lambda_.py
aibs_informatics_aws_utils/constants/s3.py
aibs_informatics_aws_utils/data_sync/__init__.py
aibs_informatics_aws_utils/data_sync/file_system.py
aibs_informatics_aws_utils/data_sync/operations.py
aibs_informatics_aws_utils/dynamodb/__init__.py
aibs_informatics_aws_utils/dynamodb/conditions.py
aibs_informatics_aws_utils/dynamodb/functions.py
aibs_informatics_aws_utils/dynamodb/table.py
aibs_informatics_aws_utils/ecr/__init__.py
aibs_informatics_aws_utils/ecr/core.py
aibs_informatics_aws_utils/ecr/image_replicator.py
aibs_informatics_aws_utils/efs/__init__.py
aibs_informatics_aws_utils/efs/core.py
aibs_informatics_aws_utils/efs/mount_point.py
aibs_informatics_aws_utils/efs/paths.py
aibs_informatics_aws_utils-0.1.1.dist-info/licenses/LICENSE
aibs_informatics_aws_utils-0.1.1.dist-info/METADATA
aibs_informatics_aws_utils-0.1.1.dist-info/WHEEL
aibs_informatics_aws_utils-0.1.1.dist-info/top_level.txt
aibs_informatics_aws_utils-0.1.1.dist-info/RECORD
