Metadata-Version: 2.4
Name: aibs-informatics-aws-utils
Version: 0.1.1
Summary: Library of AWS utility code for informatics projects at the Allen Institute for Brain Science
Author-email: AIBS Informatics Group <marmot@alleninstitute.onmicrosoft.com>
Maintainer-email: AIBS Informatics Group <marmot@alleninstitute.onmicrosoft.com>
Project-URL: Documentation, https://.github.io/aibs-informatics-aws-utils/
Project-URL: Homepage, https://github.com/AllenInstitute/aibs-informatics-aws-utils/
Project-URL: Issues, https://github.com/AllenInstitute/aibs-informatics-aws-utils/issues
Project-URL: Repository, https://github.com/AllenInstitute/aibs-informatics-aws-utils/
Requires-Python: >=3.9
License-File: LICENSE
Requires-Dist: boto3~=1.35
Requires-Dist: aibs-informatics-core<1,>=0.2.6
Requires-Dist: typing-extensions~=4.15; python_version < "3.11"
Dynamic: license-file
